AUTHORS.txt
LICENSE
MANIFEST.in
README.rst
classifiers
requirements.txt
setup.py
background_task/__init__.py
background_task/admin.py
background_task/apps.py
background_task/exceptions.py
background_task/models.py
background_task/settings.py
background_task/signals.py
background_task/tasks.py
background_task/utils.py
background_task/management/__init__.py
background_task/management/commands/__init__.py
background_task/management/commands/process_tasks.py
background_task/migrations/0001_initial.py
background_task/migrations/0002_auto_20170927_1109.py
background_task/migrations/0003_auto_20210410_1529.py
background_task/migrations/0004_auto_20220202_1721.py
background_task/migrations/__init__.py
background_task/tests/__init__.py
background_task/tests/test_settings.py
background_task/tests/test_settings_async.py
background_task/tests/test_tasks.py
django4_background_tasks.egg-info/PKG-INFO
django4_background_tasks.egg-info/SOURCES.txt
django4_background_tasks.egg-info/dependency_links.txt
django4_background_tasks.egg-info/requires.txt
django4_background_tasks.egg-info/top_level.txt
django4_background_tasks.egg-info/zip-safe